[
  {
    "turn": 0,
    "agent": "0",
    "text": "Thank you for contacting Amazon Customer Service.",
    "tokens": {
      "thank": {
        "id": "1",
        "text": "Thank",
        "lemma": "thank",
        "upos": "VERB",
        "xpos": "VBP",
        "feats": "Mood=Ind|Tense=Pres|VerbForm=Fin",
        "head": 0,
        "deprel": "root",
        "misc": "start_char=0|end_char=5"
      },
      "you": {
        "id": "2",
        "text": "you",
        "lemma": "you",
        "upos": "PRON",
        "xpos": "PRP",
        "feats": "Case=Acc|Person=2|PronType=Prs",
        "head": 1,
        "deprel": "obj",
        "misc": "start_char=6|end_char=9"
      },
      "for": {
        "id": "3",
        "text": "for",
        "lemma": "for",
        "upos": "SCONJ",
        "xpos": "IN",
        "head": 4,
        "deprel": "mark",
        "misc": "start_char=10|end_char=13"
      },
      "contact": {
        "id": "4",
        "text": "contacting",
        "lemma": "contact",
        "upos": "VERB",
        "xpos": "VBG",
        "feats": "VerbForm=Ger",
        "head": 1,
        "deprel": "advcl",
        "misc": "start_char=14|end_char=24"
      },
      "Amazon": {
        "id": "5",
        "text": "Amazon",
        "lemma": "Amazon",
        "upos": "PROPN",
        "xpos": "NNP",
        "feats": "Number=Sing",
        "head": 7,
        "deprel": "compound",
        "misc": "start_char=25|end_char=31"
      },
      "customer": {
        "id": "6",
        "text": "Customer",
        "lemma": "customer",
        "upos": "PROPN",
        "xpos": "NNP",
        "feats": "Number=Sing",
        "head": 7,
        "deprel": "compound",
        "misc": "start_char=32|end_char=40"
      },
      "Service": {
        "id": "7",
        "text": "Service",
        "lemma": "Service",
        "upos": "PROPN",
        "xpos": "NNP",
        "feats": "Number=Sing",
        "head": 4,
        "deprel": "obj",
        "misc": "start_char=41|end_char=48"
      },
      ".": {
        "id": "8",
        "text": ".",
        "lemma": ".",
        "upos": "PUNCT",
        "xpos": ".",
        "head": 1,
        "deprel": "punct",
        "misc": "start_char=48|end_char=49"
      }
    },
    "intent": "thanking",
    "semantic_slot": "others",
    "topics": [
      "thank",
      "contact",
      "Amazon",
      "customer",
      "Service"
    ]
  },
  {
    "turn": 1,
    "agent": "0",
    "text": "How may I help you today?",
    "tokens": {
      "how": {
        "id": "1",
        "text": "How",
        "lemma": "how",
        "upos": "ADV",
        "xpos": "WRB",
        "feats": "PronType=Int",
        "head": 4,
        "deprel": "advmod",
        "misc": "start_char=0|end_char=3"
      },
      "may": {
        "id": "2",
        "text": "may",
        "lemma": "may",
        "upos": "AUX",
        "xpos": "MD",
        "feats": "VerbForm=Fin",
        "head": 4,
        "deprel": "aux",
        "misc": "start_char=4|end_char=7"
      },
      "I": {
        "id": "3",
        "text": "I",
        "lemma": "I",
        "upos": "PRON",
        "xpos": "PRP",
        "feats": "Case=Nom|Number=Sing|Person=1|PronType=Prs",
        "head": 4,
        "deprel": "nsubj",
        "misc": "start_char=8|end_char=9"
      },
      "help": {
        "id": "4",
        "text": "help",
        "lemma": "help",
        "upos": "VERB",
        "xpos": "VB",
        "feats": "VerbForm=Inf",
        "head": 0,
        "deprel": "root",
        "misc": "start_char=10|end_char=14"
      },
      "you": {
        "id": "5",
        "text": "you",
        "lemma": "you",
        "upos": "PRON",
        "xpos": "PRP",
        "feats": "Case=Acc|Person=2|PronType=Prs",
        "head": 4,
        "deprel": "obj",
        "misc": "start_char=15|end_char=18"
      },
      "today": {
        "id": "6",
        "text": "today",
        "lemma": "today",
        "upos": "NOUN",
        "xpos": "NN",
        "feats": "Number=Sing",
        "head": 4,
        "deprel": "obl:tmod",
        "misc": "start_char=19|end_char=24"
      },
      "?": {
        "id": "7",
        "text": "?",
        "lemma": "?",
        "upos": "PUNCT",
        "xpos": ".",
        "head": 4,
        "deprel": "punct",
        "misc": "start_char=24|end_char=25"
      }
    },
    "intent": "open_question",
    "semantic_slot": "others",
    "topics": [
      "I",
      "help",
      "today"
    ]
  },
  {
    "turn": 2,
    "agent": "1",
    "text": "\"Hi , I ordered a heater and it was damaged\"",
    "tokens": {
      "hi": {
        "id": "1",
        "text": "Hi",
        "lemma": "hi",
        "upos": "INTJ",
        "xpos": "UH",
        "head": 4,
        "deprel": "discourse",
        "misc": "start_char=0|end_char=2"
      },
      ",": {
        "id": "2",
        "text": ",",
        "lemma": ",",
        "upos": "PUNCT",
        "xpos": ",",
        "head": 4,
        "deprel": "punct",
        "misc": "start_char=3|end_char=4"
      },
      "I": {
        "id": "3",
        "text": "I",
        "lemma": "I",
        "upos": "PRON",
        "xpos": "PRP",
        "feats": "Case=Nom|Number=Sing|Person=1|PronType=Prs",
        "head": 4,
        "deprel": "nsubj",
        "misc": "start_char=5|end_char=6"
      },
      "order": {
        "id": "4",
        "text": "ordered",
        "lemma": "order",
        "upos": "VERB",
        "xpos": "VBD",
        "feats": "Mood=Ind|Tense=Past|VerbForm=Fin",
        "head": 0,
        "deprel": "root",
        "misc": "start_char=7|end_char=14"
      },
      "a": {
        "id": "5",
        "text": "a",
        "lemma": "a",
        "upos": "DET",
        "xpos": "DT",
        "feats": "Definite=Ind|PronType=Art",
        "head": 6,
        "deprel": "det",
        "misc": "start_char=15|end_char=16"
      },
      "heater": {
        "id": "6",
        "text": "heater",
        "lemma": "heater",
        "upos": "NOUN",
        "xpos": "NN",
        "feats": "Number=Sing",
        "head": 4,
        "deprel": "obj",
        "misc": "start_char=17|end_char=23"
      },
      "and": {
        "id": "7",
        "text": "and",
        "lemma": "and",
        "upos": "CCONJ",
        "xpos": "CC",
        "head": 10,
        "deprel": "cc",
        "misc": "start_char=24|end_char=27"
      },
      "it": {
        "id": "8",
        "text": "it",
        "lemma": "it",
        "upos": "PRON",
        "xpos": "PRP",
        "feats": "Case=Nom|Gender=Neut|Number=Sing|Person=3|PronType=Prs",
        "head": 10,
        "deprel": "nsubj:pass",
        "misc": "start_char=28|end_char=30"
      },
      "be": {
        "id": "9",
        "text": "was",
        "lemma": "be",
        "upos": "AUX",
        "xpos": "VBD",
        "feats": "Mood=Ind|Number=Sing|Person=3|Tense=Past|VerbForm=Fin",
        "head": 10,
        "deprel": "aux:pass",
        "misc": "start_char=31|end_char=34"
      },
      "damage": {
        "id": "10",
        "text": "damaged",
        "lemma": "damage",
        "upos": "VERB",
        "xpos": "VBN",
        "feats": "Tense=Past|VerbForm=Part|Voice=Pass",
        "head": 4,
        "deprel": "conj",
        "misc": "start_char=35|end_char=42"
      }
    },
    "intent": "responsive_statement",
    "semantic_slot": "order_detail",
    "topics": [
      "I",
      "order",
      "heater",
      "damage"
    ]
  },
  {
    "turn": 3,
    "agent": "0",
    "text": "I apologize.",
    "tokens": {
      "I": {
        "id": "1",
        "text": "I",
        "lemma": "I",
        "upos": "PRON",
        "xpos": "PRP",
        "feats": "Case=Nom|Number=Sing|Person=1|PronType=Prs",
        "head": 2,
        "deprel": "nsubj",
        "misc": "start_char=0|end_char=1"
      },
      "apologize": {
        "id": "2",
        "text": "apologize",
        "lemma": "apologize",
        "upos": "VERB",
        "xpos": "VBP",
        "feats": "Mood=Ind|Tense=Pres|VerbForm=Fin",
        "head": 0,
        "deprel": "root",
        "misc": "start_char=2|end_char=11"
      },
      ".": {
        "id": "3",
        "text": ".",
        "lemma": ".",
        "upos": "PUNCT",
        "xpos": ".",
        "head": 2,
        "deprel": "punct",
        "misc": "start_char=11|end_char=12"
      }
    },
    "intent": "apology",
    "semantic_slot": "order_detail",
    "topics": [
      "I",
      "apologize"
    ]
  },
  {
    "turn": 4,
    "agent": "0",
    "text": "Can you verify your name and billing address so I can look that up?",
    "tokens": {
      "can": {
        "id": "11",
        "text": "can",
        "lemma": "can",
        "upos": "AUX",
        "xpos": "MD",
        "feats": "VerbForm=Fin",
        "head": 12,
        "deprel": "aux",
        "misc": "start_char=50|end_char=53"
      },
      "you": {
        "id": "4",
        "text": "your",
        "lemma": "you",
        "upos": "PRON",
        "xpos": "PRP$",
        "feats": "Person=2|Poss=Yes|PronType=Prs",
        "head": 8,
        "deprel": "nmod:poss",
        "misc": "start_char=15|end_char=19"
      },
      "verify": {
        "id": "3",
        "text": "verify",
        "lemma": "verify",
        "upos": "VERB",
        "xpos": "VB",
        "feats": "VerbForm=Inf",
        "head": 0,
        "deprel": "root",
        "misc": "start_char=8|end_char=14"
      },
      "name": {
        "id": "5",
        "text": "name",
        "lemma": "name",
        "upos": "NOUN",
        "xpos": "NN",
        "feats": "Number=Sing",
        "head": 8,
        "deprel": "compound",
        "misc": "start_char=20|end_char=24"
      },
      "and": {
        "id": "6",
        "text": "and",
        "lemma": "and",
        "upos": "CCONJ",
        "xpos": "CC",
        "head": 8,
        "deprel": "cc",
        "misc": "start_char=25|end_char=28"
      },
      "billing": {
        "id": "7",
        "text": "billing",
        "lemma": "billing",
        "upos": "NOUN",
        "xpos": "NN",
        "feats": "Number=Sing",
        "head": 5,
        "deprel": "conj",
        "misc": "start_char=29|end_char=36"
      },
      "address": {
        "id": "8",
        "text": "address",
        "lemma": "address",
        "upos": "NOUN",
        "xpos": "NN",
        "feats": "Number=Sing",
        "head": 3,
        "deprel": "obj",
        "misc": "start_char=37|end_char=44"
      },
      "so": {
        "id": "9",
        "text": "so",
        "lemma": "so",
        "upos": "SCONJ",
        "xpos": "IN",
        "head": 12,
        "deprel": "mark",
        "misc": "start_char=45|end_char=47"
      },
      "I": {
        "id": "10",
        "text": "I",
        "lemma": "I",
        "upos": "PRON",
        "xpos": "PRP",
        "feats": "Case=Nom|Number=Sing|Person=1|PronType=Prs",
        "head": 12,
        "deprel": "nsubj",
        "misc": "start_char=48|end_char=49"
      },
      "look": {
        "id": "12",
        "text": "look",
        "lemma": "look",
        "upos": "VERB",
        "xpos": "VB",
        "feats": "VerbForm=Inf",
        "head": 3,
        "deprel": "advcl",
        "misc": "start_char=54|end_char=58"
      },
      "that": {
        "id": "13",
        "text": "that",
        "lemma": "that",
        "upos": "PRON",
        "xpos": "DT",
        "feats": "Number=Sing|PronType=Dem",
        "head": 12,
        "deprel": "obj",
        "misc": "start_char=59|end_char=63"
      },
      "up": {
        "id": "14",
        "text": "up",
        "lemma": "up",
        "upos": "ADP",
        "xpos": "RP",
        "head": 12,
        "deprel": "compound:prt",
        "misc": "start_char=64|end_char=66"
      },
      "?": {
        "id": "15",
        "text": "?",
        "lemma": "?",
        "upos": "PUNCT",
        "xpos": ".",
        "head": 3,
        "deprel": "punct",
        "misc": "start_char=66|end_char=67"
      }
    },
    "intent": "elicitation",
    "semantic_slot": "name",
    "topics": [
      "verify",
      "name",
      "billing",
      "address",
      "I",
      "look"
    ]
  },
  {
    "turn": 5,
    "agent": "1",
    "text": "NAMESLOTU",
    "tokens": {
      "nameslotu": {
        "id": "1",
        "text": "NAMESLOTU",
        "lemma": "nameslotu",
        "upos": "ADJ",
        "xpos": "JJ",
        "feats": "Degree=Pos",
        "head": 0,
        "deprel": "root",
        "misc": "start_char=0|end_char=9"
      }
    },
    "intent": "provide",
    "semantic_slot": "name",
    "topics": []
  },
  {
    "turn": 6,
    "agent": "0",
    "text": "\"Thank you, and your billing address?\"",
    "tokens": {
      "thank": {
        "id": "1",
        "text": "Thank",
        "lemma": "thank",
        "upos": "VERB",
        "xpos": "VBP",
        "feats": "Mood=Ind|Tense=Pres|VerbForm=Fin",
        "head": 0,
        "deprel": "root",
        "misc": "start_char=0|end_char=5"
      },
      "you": {
        "id": "5",
        "text": "your",
        "lemma": "you",
        "upos": "PRON",
        "xpos": "PRP$",
        "feats": "Person=2|Poss=Yes|PronType=Prs",
        "head": 7,
        "deprel": "nmod:poss",
        "misc": "start_char=15|end_char=19"
      },
      ",": {
        "id": "3",
        "text": ",",
        "lemma": ",",
        "upos": "PUNCT",
        "xpos": ",",
        "head": 7,
        "deprel": "punct",
        "misc": "start_char=9|end_char=10"
      },
      "and": {
        "id": "4",
        "text": "and",
        "lemma": "and",
        "upos": "CCONJ",
        "xpos": "CC",
        "head": 7,
        "deprel": "cc",
        "misc": "start_char=11|end_char=14"
      },
      "billing": {
        "id": "6",
        "text": "billing",
        "lemma": "billing",
        "upos": "NOUN",
        "xpos": "NN",
        "feats": "Number=Sing",
        "head": 7,
        "deprel": "compound",
        "misc": "start_char=20|end_char=27"
      },
      "address": {
        "id": "7",
        "text": "address",
        "lemma": "address",
        "upos": "NOUN",
        "xpos": "NN",
        "feats": "Number=Sing",
        "head": 2,
        "deprel": "conj",
        "misc": "start_char=28|end_char=35"
      },
      "?": {
        "id": "8",
        "text": "?",
        "lemma": "?",
        "upos": "PUNCT",
        "xpos": ".",
        "head": 1,
        "deprel": "punct",
        "misc": "start_char=35|end_char=36"
      }
    },
    "intent": "elicitation",
    "semantic_slot": "address",
    "topics": [
      "thank",
      "billing",
      "address"
    ]
  },
  {
    "turn": 7,
    "agent": "1",
    "text": "ADDRSLOT",
    "tokens": {
      "addrslot": {
        "id": "1",
        "text": "ADDRSLOT",
        "lemma": "addrslot",
        "upos": "ADJ",
        "xpos": "JJ",
        "feats": "Degree=Pos",
        "head": 0,
        "deprel": "root",
        "misc": "start_char=0|end_char=8"
      }
    },
    "intent": "provide",
    "semantic_slot": "address",
    "topics": []
  },
  {
    "turn": 8,
    "agent": "0",
    "text": "\"Great, one moment while I look up your order history. \"",
    "tokens": {
      "great": {
        "id": "1",
        "text": "Great",
        "lemma": "great",
        "upos": "ADJ",
        "xpos": "JJ",
        "feats": "Degree=Pos",
        "head": 0,
        "deprel": "root",
        "misc": "start_char=0|end_char=5"
      },
      ",": {
        "id": "2",
        "text": ",",
        "lemma": ",",
        "upos": "PUNCT",
        "xpos": ",",
        "head": 1,
        "deprel": "punct",
        "misc": "start_char=5|end_char=6"
      },
      "one": {
        "id": "3",
        "text": "one",
        "lemma": "one",
        "upos": "NUM",
        "xpos": "CD",
        "feats": "NumType=Card",
        "head": 4,
        "deprel": "nummod",
        "misc": "start_char=7|end_char=10"
      },
      "moment": {
        "id": "4",
        "text": "moment",
        "lemma": "moment",
        "upos": "NOUN",
        "xpos": "NN",
        "feats": "Number=Sing",
        "head": 1,
        "deprel": "parataxis",
        "misc": "start_char=11|end_char=17"
      },
      "while": {
        "id": "5",
        "text": "while",
        "lemma": "while",
        "upos": "SCONJ",
        "xpos": "IN",
        "head": 7,
        "deprel": "mark",
        "misc": "start_char=18|end_char=23"
      },
      "I": {
        "id": "6",
        "text": "I",
        "lemma": "I",
        "upos": "PRON",
        "xpos": "PRP",
        "feats": "Case=Nom|Number=Sing|Person=1|PronType=Prs",
        "head": 7,
        "deprel": "nsubj",
        "misc": "start_char=24|end_char=25"
      },
      "look": {
        "id": "7",
        "text": "look",
        "lemma": "look",
        "upos": "VERB",
        "xpos": "VBP",
        "feats": "Mood=Ind|Tense=Pres|VerbForm=Fin",
        "head": 4,
        "deprel": "advcl",
        "misc": "start_char=26|end_char=30"
      },
      "up": {
        "id": "8",
        "text": "up",
        "lemma": "up",
        "upos": "ADP",
        "xpos": "RP",
        "head": 7,
        "deprel": "compound:prt",
        "misc": "start_char=31|end_char=33"
      },
      "you": {
        "id": "9",
        "text": "your",
        "lemma": "you",
        "upos": "PRON",
        "xpos": "PRP$",
        "feats": "Person=2|Poss=Yes|PronType=Prs",
        "head": 11,
        "deprel": "nmod:poss",
        "misc": "start_char=34|end_char=38"
      },
      "order": {
        "id": "10",
        "text": "order",
        "lemma": "order",
        "upos": "NOUN",
        "xpos": "NN",
        "feats": "Number=Sing",
        "head": 11,
        "deprel": "compound",
        "misc": "start_char=39|end_char=44"
      },
      "history": {
        "id": "11",
        "text": "history",
        "lemma": "history",
        "upos": "NOUN",
        "xpos": "NN",
        "feats": "Number=Sing",
        "head": 7,
        "deprel": "obj",
        "misc": "start_char=45|end_char=52"
      },
      ".": {
        "id": "12",
        "text": ".",
        "lemma": ".",
        "upos": "PUNCT",
        "xpos": ".",
        "head": 1,
        "deprel": "punct",
        "misc": "start_char=52|end_char=53"
      }
    },
    "intent": "nonresponsive_statement",
    "semantic_slot": "others",
    "topics": [
      "moment",
      "I",
      "look",
      "order",
      "history"
    ]
  },
  {
    "turn": 9,
    "agent": "1",
    "text": "Ok Thanks",
    "tokens": {
      "ok": {
        "id": "1",
        "text": "Ok",
        "lemma": "ok",
        "upos": "INTJ",
        "xpos": "UH",
        "head": 0,
        "deprel": "root",
        "misc": "start_char=0|end_char=2"
      },
      "thanks": {
        "id": "1",
        "text": "Thanks",
        "lemma": "thanks",
        "upos": "NOUN",
        "xpos": "NN",
        "feats": "Number=Sing",
        "head": 0,
        "deprel": "root",
        "misc": "start_char=3|end_char=9"
      }
    },
    "intent": "thanking",
    "semantic_slot": "others",
    "topics": [
      "thanks"
    ]
  },
  {
    "turn": 10,
    "agent": "0",
    "text": "I have located your order and can provide a refund to the card you paid with.",
    "tokens": {
      "I": {
        "id": "1",
        "text": "I",
        "lemma": "I",
        "upos": "PRON",
        "xpos": "PRP",
        "feats": "Case=Nom|Number=Sing|Person=1|PronType=Prs",
        "head": 3,
        "deprel": "nsubj",
        "misc": "start_char=0|end_char=1"
      },
      "have": {
        "id": "2",
        "text": "have",
        "lemma": "have",
        "upos": "AUX",
        "xpos": "VBP",
        "feats": "Mood=Ind|Tense=Pres|VerbForm=Fin",
        "head": 3,
        "deprel": "aux",
        "misc": "start_char=2|end_char=6"
      },
      "locate": {
        "id": "3",
        "text": "located",
        "lemma": "locate",
        "upos": "VERB",
        "xpos": "VBN",
        "feats": "Tense=Past|VerbForm=Part",
        "head": 0,
        "deprel": "root",
        "misc": "start_char=7|end_char=14"
      },
      "you": {
        "id": "14",
        "text": "you",
        "lemma": "you",
        "upos": "PRON",
        "xpos": "PRP",
        "feats": "Case=Nom|Person=2|PronType=Prs",
        "head": 15,
        "deprel": "nsubj",
        "misc": "start_char=63|end_char=66"
      },
      "order": {
        "id": "5",
        "text": "order",
        "lemma": "order",
        "upos": "NOUN",
        "xpos": "NN",
        "feats": "Number=Sing",
        "head": 3,
        "deprel": "obj",
        "misc": "start_char=20|end_char=25"
      },
      "and": {
        "id": "6",
        "text": "and",
        "lemma": "and",
        "upos": "CCONJ",
        "xpos": "CC",
        "head": 8,
        "deprel": "cc",
        "misc": "start_char=26|end_char=29"
      },
      "can": {
        "id": "7",
        "text": "can",
        "lemma": "can",
        "upos": "AUX",
        "xpos": "MD",
        "feats": "VerbForm=Fin",
        "head": 8,
        "deprel": "aux",
        "misc": "start_char=30|end_char=33"
      },
      "provide": {
        "id": "8",
        "text": "provide",
        "lemma": "provide",
        "upos": "VERB",
        "xpos": "VB",
        "feats": "VerbForm=Inf",
        "head": 3,
        "deprel": "conj",
        "misc": "start_char=34|end_char=41"
      },
      "a": {
        "id": "9",
        "text": "a",
        "lemma": "a",
        "upos": "DET",
        "xpos": "DT",
        "feats": "Definite=Ind|PronType=Art",
        "head": 10,
        "deprel": "det",
        "misc": "start_char=42|end_char=43"
      },
      "refund": {
        "id": "10",
        "text": "refund",
        "lemma": "refund",
        "upos": "NOUN",
        "xpos": "NN",
        "feats": "Number=Sing",
        "head": 8,
        "deprel": "obj",
        "misc": "start_char=44|end_char=50"
      },
      "to": {
        "id": "11",
        "text": "to",
        "lemma": "to",
        "upos": "ADP",
        "xpos": "IN",
        "head": 13,
        "deprel": "case",
        "misc": "start_char=51|end_char=53"
      },
      "the": {
        "id": "12",
        "text": "the",
        "lemma": "the",
        "upos": "DET",
        "xpos": "DT",
        "feats": "Definite=Def|PronType=Art",
        "head": 13,
        "deprel": "det",
        "misc": "start_char=54|end_char=57"
      },
      "card": {
        "id": "13",
        "text": "card",
        "lemma": "card",
        "upos": "NOUN",
        "xpos": "NN",
        "feats": "Number=Sing",
        "head": 10,
        "deprel": "nmod",
        "misc": "start_char=58|end_char=62"
      },
      "pay": {
        "id": "15",
        "text": "paid",
        "lemma": "pay",
        "upos": "VERB",
        "xpos": "VBD",
        "feats": "Mood=Ind|Tense=Past|VerbForm=Fin",
        "head": 13,
        "deprel": "acl:relcl",
        "misc": "start_char=67|end_char=71"
      },
      "with": {
        "id": "16",
        "text": "with",
        "lemma": "with",
        "upos": "ADP",
        "xpos": "IN",
        "head": 15,
        "deprel": "obl",
        "misc": "start_char=72|end_char=76"
      },
      ".": {
        "id": "17",
        "text": ".",
        "lemma": ".",
        "upos": "PUNCT",
        "xpos": ".",
        "head": 3,
        "deprel": "punct",
        "misc": "start_char=76|end_char=77"
      }
    },
    "intent": "nonresponsive_statement",
    "semantic_slot": "order_update",
    "topics": [
      "I",
      "locate",
      "order",
      "provide",
      "refund",
      "card",
      "pay"
    ]
  },
  {
    "turn": 11,
    "agent": "1",
    "text": "That sounds great",
    "tokens": {
      "that": {
        "id": "1",
        "text": "That",
        "lemma": "that",
        "upos": "PRON",
        "xpos": "DT",
        "feats": "Number=Sing|PronType=Dem",
        "head": 2,
        "deprel": "nsubj",
        "misc": "start_char=0|end_char=4"
      },
      "sound": {
        "id": "2",
        "text": "sounds",
        "lemma": "sound",
        "upos": "VERB",
        "xpos": "VBZ",
        "feats": "Mood=Ind|Number=Sing|Person=3|Tense=Pres|VerbForm=Fin",
        "head": 0,
        "deprel": "root",
        "misc": "start_char=5|end_char=11"
      },
      "great": {
        "id": "3",
        "text": "great",
        "lemma": "great",
        "upos": "ADJ",
        "xpos": "JJ",
        "feats": "Degree=Pos",
        "head": 2,
        "deprel": "xcomp",
        "misc": "start_char=12|end_char=17"
      }
    },
    "intent": "nonresponsive_statement",
    "semantic_slot": "others",
    "topics": []
  },
  {
    "turn": 12,
    "agent": "0",
    "text": "Great.",
    "tokens": {
      "great": {
        "id": "1",
        "text": "Great",
        "lemma": "great",
        "upos": "ADJ",
        "xpos": "JJ",
        "feats": "Degree=Pos",
        "head": 0,
        "deprel": "root",
        "misc": "start_char=0|end_char=5"
      },
      ".": {
        "id": "2",
        "text": ".",
        "lemma": ".",
        "upos": "PUNCT",
        "xpos": ".",
        "head": 1,
        "deprel": "punct",
        "misc": "start_char=5|end_char=6"
      }
    },
    "intent": "hold",
    "semantic_slot": "others",
    "topics": []
  },
  {
    "turn": 13,
    "agent": "0",
    "text": "\"To begin, I will need the card number and expiration date\"",
    "tokens": {
      "to": {
        "id": "1",
        "text": "To",
        "lemma": "to",
        "upos": "PART",
        "xpos": "TO",
        "head": 2,
        "deprel": "mark",
        "misc": "start_char=0|end_char=2"
      },
      "begin": {
        "id": "2",
        "text": "begin",
        "lemma": "begin",
        "upos": "VERB",
        "xpos": "VB",
        "feats": "VerbForm=Inf",
        "head": 6,
        "deprel": "advcl",
        "misc": "start_char=3|end_char=8"
      },
      ",": {
        "id": "3",
        "text": ",",
        "lemma": ",",
        "upos": "PUNCT",
        "xpos": ",",
        "head": 6,
        "deprel": "punct",
        "misc": "start_char=8|end_char=9"
      },
      "I": {
        "id": "4",
        "text": "I",
        "lemma": "I",
        "upos": "PRON",
        "xpos": "PRP",
        "feats": "Case=Nom|Number=Sing|Person=1|PronType=Prs",
        "head": 6,
        "deprel": "nsubj",
        "misc": "start_char=10|end_char=11"
      },
      "will": {
        "id": "5",
        "text": "will",
        "lemma": "will",
        "upos": "AUX",
        "xpos": "MD",
        "feats": "VerbForm=Fin",
        "head": 6,
        "deprel": "aux",
        "misc": "start_char=12|end_char=16"
      },
      "need": {
        "id": "6",
        "text": "need",
        "lemma": "need",
        "upos": "VERB",
        "xpos": "VB",
        "feats": "VerbForm=Inf",
        "head": 0,
        "deprel": "root",
        "misc": "start_char=17|end_char=21"
      },
      "the": {
        "id": "7",
        "text": "the",
        "lemma": "the",
        "upos": "DET",
        "xpos": "DT",
        "feats": "Definite=Def|PronType=Art",
        "head": 9,
        "deprel": "det",
        "misc": "start_char=22|end_char=25"
      },
      "card": {
        "id": "8",
        "text": "card",
        "lemma": "card",
        "upos": "NOUN",
        "xpos": "NN",
        "feats": "Number=Sing",
        "head": 9,
        "deprel": "compound",
        "misc": "start_char=26|end_char=30"
      },
      "number": {
        "id": "9",
        "text": "number",
        "lemma": "number",
        "upos": "NOUN",
        "xpos": "NN",
        "feats": "Number=Sing",
        "head": 6,
        "deprel": "obj",
        "misc": "start_char=31|end_char=37"
      },
      "and": {
        "id": "10",
        "text": "and",
        "lemma": "and",
        "upos": "CCONJ",
        "xpos": "CC",
        "head": 12,
        "deprel": "cc",
        "misc": "start_char=38|end_char=41"
      },
      "expiration": {
        "id": "11",
        "text": "expiration",
        "lemma": "expiration",
        "upos": "NOUN",
        "xpos": "NN",
        "feats": "Number=Sing",
        "head": 12,
        "deprel": "compound",
        "misc": "start_char=42|end_char=52"
      },
      "date": {
        "id": "12",
        "text": "date",
        "lemma": "date",
        "upos": "NOUN",
        "xpos": "NN",
        "feats": "Number=Sing",
        "head": 9,
        "deprel": "conj",
        "misc": "start_char=53|end_char=57"
      }
    },
    "intent": "elicitation",
    "semantic_slot": "card_info",
    "topics": [
      "begin",
      "I",
      "need",
      "card",
      "number",
      "expiration",
      "date"
    ]
  },
  {
    "turn": 14,
    "agent": "1",
    "text": "\"NUMSLOT, DATESLOT\"",
    "tokens": {
      "NUMSLOT": {
        "id": "1",
        "text": "NUMSLOT",
        "lemma": "NUMSLOT",
        "upos": "PROPN",
        "xpos": "NNP",
        "feats": "Number=Sing",
        "head": 0,
        "deprel": "root",
        "misc": "start_char=0|end_char=7"
      },
      ",": {
        "id": "2",
        "text": ",",
        "lemma": ",",
        "upos": "PUNCT",
        "xpos": ",",
        "head": 1,
        "deprel": "punct",
        "misc": "start_char=7|end_char=8"
      },
      "dateslot": {
        "id": "3",
        "text": "DATESLOT",
        "lemma": "dateslot",
        "upos": "ADJ",
        "xpos": "JJ",
        "feats": "Degree=Pos",
        "head": 1,
        "deprel": "parataxis",
        "misc": "start_char=9|end_char=17"
      }
    },
    "intent": "provide",
    "semantic_slot": "card_num",
    "topics": [
      "NUMSLOT"
    ]
  },
  {
    "turn": 15,
    "agent": "0",
    "text": "Thank you.",
    "tokens": {
      "thank": {
        "id": "1",
        "text": "Thank",
        "lemma": "thank",
        "upos": "VERB",
        "xpos": "VBP",
        "feats": "Mood=Ind|Tense=Pres|VerbForm=Fin",
        "head": 0,
        "deprel": "root",
        "misc": "start_char=0|end_char=5"
      },
      "you": {
        "id": "2",
        "text": "you",
        "lemma": "you",
        "upos": "PRON",
        "xpos": "PRP",
        "feats": "Case=Acc|Person=2|PronType=Prs",
        "head": 1,
        "deprel": "obj",
        "misc": "start_char=6|end_char=9"
      },
      ".": {
        "id": "3",
        "text": ".",
        "lemma": ".",
        "upos": "PUNCT",
        "xpos": ".",
        "head": 1,
        "deprel": "punct",
        "misc": "start_char=9|end_char=10"
      }
    },
    "intent": "thanking",
    "semantic_slot": "card_info",
    "topics": [
      "thank"
    ]
  },
  {
    "turn": 16,
    "agent": "0",
    "text": "\"Next, I will need the CSV number from that card. \"",
    "tokens": {
      "next": {
        "id": "1",
        "text": "Next",
        "lemma": "next",
        "upos": "ADV",
        "xpos": "RB",
        "head": 5,
        "deprel": "advmod",
        "misc": "start_char=0|end_char=4"
      },
      ",": {
        "id": "2",
        "text": ",",
        "lemma": ",",
        "upos": "PUNCT",
        "xpos": ",",
        "head": 5,
        "deprel": "punct",
        "misc": "start_char=4|end_char=5"
      },
      "I": {
        "id": "3",
        "text": "I",
        "lemma": "I",
        "upos": "PRON",
        "xpos": "PRP",
        "feats": "Case=Nom|Number=Sing|Person=1|PronType=Prs",
        "head": 5,
        "deprel": "nsubj",
        "misc": "start_char=6|end_char=7"
      },
      "will": {
        "id": "4",
        "text": "will",
        "lemma": "will",
        "upos": "AUX",
        "xpos": "MD",
        "feats": "VerbForm=Fin",
        "head": 5,
        "deprel": "aux",
        "misc": "start_char=8|end_char=12"
      },
      "need": {
        "id": "5",
        "text": "need",
        "lemma": "need",
        "upos": "VERB",
        "xpos": "VB",
        "feats": "VerbForm=Inf",
        "head": 0,
        "deprel": "root",
        "misc": "start_char=13|end_char=17"
      },
      "the": {
        "id": "6",
        "text": "the",
        "lemma": "the",
        "upos": "DET",
        "xpos": "DT",
        "feats": "Definite=Def|PronType=Art",
        "head": 8,
        "deprel": "det",
        "misc": "start_char=18|end_char=21"
      },
      "csv": {
        "id": "7",
        "text": "CSV",
        "lemma": "csv",
        "upos": "NOUN",
        "xpos": "NN",
        "feats": "Number=Sing",
        "head": 8,
        "deprel": "compound",
        "misc": "start_char=22|end_char=25"
      },
      "number": {
        "id": "8",
        "text": "number",
        "lemma": "number",
        "upos": "NOUN",
        "xpos": "NN",
        "feats": "Number=Sing",
        "head": 5,
        "deprel": "obj",
        "misc": "start_char=26|end_char=32"
      },
      "from": {
        "id": "9",
        "text": "from",
        "lemma": "from",
        "upos": "ADP",
        "xpos": "IN",
        "head": 11,
        "deprel": "case",
        "misc": "start_char=33|end_char=37"
      },
      "that": {
        "id": "10",
        "text": "that",
        "lemma": "that",
        "upos": "DET",
        "xpos": "DT",
        "feats": "Number=Sing|PronType=Dem",
        "head": 11,
        "deprel": "det",
        "misc": "start_char=38|end_char=42"
      },
      "card": {
        "id": "11",
        "text": "card",
        "lemma": "card",
        "upos": "NOUN",
        "xpos": "NN",
        "feats": "Number=Sing",
        "head": 8,
        "deprel": "nmod",
        "misc": "start_char=43|end_char=47"
      },
      ".": {
        "id": "12",
        "text": ".",
        "lemma": ".",
        "upos": "PUNCT",
        "xpos": ".",
        "head": 5,
        "deprel": "punct",
        "misc": "start_char=47|end_char=48"
      }
    },
    "intent": "elicitation",
    "semantic_slot": "card_csv",
    "topics": [
      "I",
      "need",
      "csv",
      "number",
      "card"
    ]
  },
  {
    "turn": 17,
    "agent": "1",
    "text": "CSVSLOT",
    "tokens": {
      "CSVSLOT": {
        "id": "1",
        "text": "CSVSLOT",
        "lemma": "CSVSLOT",
        "upos": "PROPN",
        "xpos": "NNP",
        "feats": "Number=Sing",
        "head": 0,
        "deprel": "root",
        "misc": "start_char=0|end_char=7"
      }
    },
    "intent": "provide",
    "semantic_slot": "card_csv",
    "topics": [
      "CSVSLOT"
    ]
  },
  {
    "turn": 18,
    "agent": "0",
    "text": "\"Thank you, give me a moment while I enter that information. \"",
    "tokens": {
      "thank": {
        "id": "1",
        "text": "Thank",
        "lemma": "thank",
        "upos": "VERB",
        "xpos": "VBP",
        "feats": "Mood=Ind|Tense=Pres|VerbForm=Fin",
        "head": 0,
        "deprel": "root",
        "misc": "start_char=0|end_char=5"
      },
      "you": {
        "id": "2",
        "text": "you",
        "lemma": "you",
        "upos": "PRON",
        "xpos": "PRP",
        "feats": "Case=Acc|Person=2|PronType=Prs",
        "head": 1,
        "deprel": "obj",
        "misc": "start_char=6|end_char=9"
      },
      ",": {
        "id": "3",
        "text": ",",
        "lemma": ",",
        "upos": "PUNCT",
        "xpos": ",",
        "head": 1,
        "deprel": "punct",
        "misc": "start_char=9|end_char=10"
      },
      "give": {
        "id": "4",
        "text": "give",
        "lemma": "give",
        "upos": "VERB",
        "xpos": "VB",
        "feats": "Mood=Imp|VerbForm=Fin",
        "head": 1,
        "deprel": "parataxis",
        "misc": "start_char=11|end_char=15"
      },
      "I": {
        "id": "9",
        "text": "I",
        "lemma": "I",
        "upos": "PRON",
        "xpos": "PRP",
        "feats": "Case=Nom|Number=Sing|Person=1|PronType=Prs",
        "head": 10,
        "deprel": "nsubj",
        "misc": "start_char=34|end_char=35"
      },
      "a": {
        "id": "6",
        "text": "a",
        "lemma": "a",
        "upos": "DET",
        "xpos": "DT",
        "feats": "Definite=Ind|PronType=Art",
        "head": 7,
        "deprel": "det",
        "misc": "start_char=19|end_char=20"
      },
      "moment": {
        "id": "7",
        "text": "moment",
        "lemma": "moment",
        "upos": "NOUN",
        "xpos": "NN",
        "feats": "Number=Sing",
        "head": 4,
        "deprel": "obj",
        "misc": "start_char=21|end_char=27"
      },
      "while": {
        "id": "8",
        "text": "while",
        "lemma": "while",
        "upos": "SCONJ",
        "xpos": "IN",
        "head": 10,
        "deprel": "mark",
        "misc": "start_char=28|end_char=33"
      },
      "enter": {
        "id": "10",
        "text": "enter",
        "lemma": "enter",
        "upos": "VERB",
        "xpos": "VBP",
        "feats": "Mood=Ind|Tense=Pres|VerbForm=Fin",
        "head": 4,
        "deprel": "advcl",
        "misc": "start_char=36|end_char=41"
      },
      "that": {
        "id": "11",
        "text": "that",
        "lemma": "that",
        "upos": "DET",
        "xpos": "DT",
        "feats": "Number=Sing|PronType=Dem",
        "head": 12,
        "deprel": "det",
        "misc": "start_char=42|end_char=46"
      },
      "information": {
        "id": "12",
        "text": "information",
        "lemma": "information",
        "upos": "NOUN",
        "xpos": "NN",
        "feats": "Number=Sing",
        "head": 10,
        "deprel": "obj",
        "misc": "start_char=47|end_char=58"
      },
      ".": {
        "id": "13",
        "text": ".",
        "lemma": ".",
        "upos": "PUNCT",
        "xpos": ".",
        "head": 1,
        "deprel": "punct",
        "misc": "start_char=58|end_char=59"
      }
    },
    "intent": "thanking",
    "semantic_slot": "card_info",
    "topics": [
      "thank",
      "give",
      "I",
      "moment",
      "enter",
      "information"
    ]
  },
  {
    "turn": 19,
    "agent": "1",
    "text": "\"sure, take your time : )\"",
    "tokens": {
      "sure": {
        "id": "1",
        "text": "sure",
        "lemma": "sure",
        "upos": "INTJ",
        "xpos": "UH",
        "head": 3,
        "deprel": "discourse",
        "misc": "start_char=0|end_char=4"
      },
      ",": {
        "id": "2",
        "text": ",",
        "lemma": ",",
        "upos": "PUNCT",
        "xpos": ",",
        "head": 3,
        "deprel": "punct",
        "misc": "start_char=4|end_char=5"
      },
      "take": {
        "id": "3",
        "text": "take",
        "lemma": "take",
        "upos": "VERB",
        "xpos": "VB",
        "feats": "Mood=Imp|VerbForm=Fin",
        "head": 0,
        "deprel": "root",
        "misc": "start_char=6|end_char=10"
      },
      "you": {
        "id": "4",
        "text": "your",
        "lemma": "you",
        "upos": "PRON",
        "xpos": "PRP$",
        "feats": "Person=2|Poss=Yes|PronType=Prs",
        "head": 5,
        "deprel": "nmod:poss",
        "misc": "start_char=11|end_char=15"
      },
      "time": {
        "id": "5",
        "text": "time",
        "lemma": "time",
        "upos": "NOUN",
        "xpos": "NN",
        "feats": "Number=Sing",
        "head": 3,
        "deprel": "obj",
        "misc": "start_char=16|end_char=20"
      },
      ":": {
        "id": "6",
        "text": ":",
        "lemma": ":",
        "upos": "PUNCT",
        "xpos": ":",
        "head": 3,
        "deprel": "punct",
        "misc": "start_char=21|end_char=22"
      },
      ")": {
        "id": "7",
        "text": ")",
        "lemma": ")",
        "upos": "PUNCT",
        "xpos": "-RRB-",
        "head": 3,
        "deprel": "punct",
        "misc": "start_char=23|end_char=24"
      }
    },
    "intent": "response_to_thanking",
    "semantic_slot": "others",
    "topics": [
      "take",
      "time"
    ]
  },
  {
    "turn": 20,
    "agent": "0",
    "text": "Everything looks good.",
    "tokens": {
      "everything": {
        "id": "1",
        "text": "Everything",
        "lemma": "everything",
        "upos": "PRON",
        "xpos": "NN",
        "feats": "Number=Sing",
        "head": 2,
        "deprel": "nsubj",
        "misc": "start_char=0|end_char=10"
      },
      "look": {
        "id": "2",
        "text": "looks",
        "lemma": "look",
        "upos": "VERB",
        "xpos": "VBZ",
        "feats": "Mood=Ind|Number=Sing|Person=3|Tense=Pres|VerbForm=Fin",
        "head": 0,
        "deprel": "root",
        "misc": "start_char=11|end_char=16"
      },
      "good": {
        "id": "3",
        "text": "good",
        "lemma": "good",
        "upos": "ADJ",
        "xpos": "JJ",
        "feats": "Degree=Pos",
        "head": 2,
        "deprel": "xcomp",
        "misc": "start_char=17|end_char=21"
      },
      ".": {
        "id": "4",
        "text": ".",
        "lemma": ".",
        "upos": "PUNCT",
        "xpos": ".",
        "head": 2,
        "deprel": "punct",
        "misc": "start_char=21|end_char=22"
      }
    },
    "intent": "nonresponsive_statement",
    "semantic_slot": "others",
    "topics": [
      "everything"
    ]
  },
  {
    "turn": 21,
    "agent": "0",
    "text": "You should be seeing your refund in 3-7 business days",
    "tokens": {
      "you": {
        "id": "5",
        "text": "your",
        "lemma": "you",
        "upos": "PRON",
        "xpos": "PRP$",
        "feats": "Person=2|Poss=Yes|PronType=Prs",
        "head": 6,
        "deprel": "nmod:poss",
        "misc": "start_char=21|end_char=25"
      },
      "should": {
        "id": "2",
        "text": "should",
        "lemma": "should",
        "upos": "AUX",
        "xpos": "MD",
        "feats": "VerbForm=Fin",
        "head": 4,
        "deprel": "aux",
        "misc": "start_char=4|end_char=10"
      },
      "be": {
        "id": "3",
        "text": "be",
        "lemma": "be",
        "upos": "AUX",
        "xpos": "VB",
        "feats": "VerbForm=Inf",
        "head": 4,
        "deprel": "aux",
        "misc": "start_char=11|end_char=13"
      },
      "see": {
        "id": "4",
        "text": "seeing",
        "lemma": "see",
        "upos": "VERB",
        "xpos": "VBG",
        "feats": "Tense=Pres|VerbForm=Part",
        "head": 0,
        "deprel": "root",
        "misc": "start_char=14|end_char=20"
      },
      "refund": {
        "id": "6",
        "text": "refund",
        "lemma": "refund",
        "upos": "NOUN",
        "xpos": "NN",
        "feats": "Number=Sing",
        "head": 4,
        "deprel": "obj",
        "misc": "start_char=26|end_char=32"
      },
      "in": {
        "id": "7",
        "text": "in",
        "lemma": "in",
        "upos": "ADP",
        "xpos": "IN",
        "head": 12,
        "deprel": "case",
        "misc": "start_char=33|end_char=35"
      },
      "3": {
        "id": "8",
        "text": "3",
        "lemma": "3",
        "upos": "NUM",
        "xpos": "CD",
        "feats": "NumType=Card",
        "head": 12,
        "deprel": "nummod",
        "misc": "start_char=36|end_char=37"
      },
      "-": {
        "id": "9",
        "text": "-",
        "lemma": "-",
        "upos": "SYM",
        "xpos": "SYM",
        "head": 10,
        "deprel": "case",
        "misc": "start_char=37|end_char=38"
      },
      "7": {
        "id": "10",
        "text": "7",
        "lemma": "7",
        "upos": "NUM",
        "xpos": "CD",
        "feats": "NumType=Card",
        "head": 8,
        "deprel": "nmod",
        "misc": "start_char=38|end_char=39"
      },
      "business": {
        "id": "11",
        "text": "business",
        "lemma": "business",
        "upos": "NOUN",
        "xpos": "NN",
        "feats": "Number=Sing",
        "head": 12,
        "deprel": "compound",
        "misc": "start_char=40|end_char=48"
      },
      "day": {
        "id": "12",
        "text": "days",
        "lemma": "day",
        "upos": "NOUN",
        "xpos": "NNS",
        "feats": "Number=Plur",
        "head": 4,
        "deprel": "obl",
        "misc": "start_char=49|end_char=53"
      }
    },
    "intent": "nonresponsive_statement",
    "semantic_slot": "order_update",
    "topics": [
      "see",
      "refund",
      "business",
      "day"
    ]
  },
  {
    "turn": 22,
    "agent": "1",
    "text": "Great !",
    "tokens": {
      "great": {
        "id": "1",
        "text": "Great",
        "lemma": "great",
        "upos": "ADJ",
        "xpos": "JJ",
        "feats": "Degree=Pos",
        "head": 0,
        "deprel": "root",
        "misc": "start_char=0|end_char=5"
      },
      "!": {
        "id": "2",
        "text": "!",
        "lemma": "!",
        "upos": "PUNCT",
        "xpos": ".",
        "head": 1,
        "deprel": "punct",
        "misc": "start_char=6|end_char=7"
      }
    },
    "intent": "hold",
    "semantic_slot": "others",
    "topics": []
  },
  {
    "turn": 23,
    "agent": "0",
    "text": "\"In the meantime, is there anything else I can help you with?\"",
    "tokens": {
      "in": {
        "id": "1",
        "text": "In",
        "lemma": "in",
        "upos": "ADP",
        "xpos": "IN",
        "head": 3,
        "deprel": "case",
        "misc": "start_char=0|end_char=2"
      },
      "the": {
        "id": "2",
        "text": "the",
        "lemma": "the",
        "upos": "DET",
        "xpos": "DT",
        "feats": "Definite=Def|PronType=Art",
        "head": 3,
        "deprel": "det",
        "misc": "start_char=3|end_char=6"
      },
      "meantime": {
        "id": "3",
        "text": "meantime",
        "lemma": "meantime",
        "upos": "NOUN",
        "xpos": "NN",
        "feats": "Number=Sing",
        "head": 5,
        "deprel": "obl",
        "misc": "start_char=7|end_char=15"
      },
      ",": {
        "id": "4",
        "text": ",",
        "lemma": ",",
        "upos": "PUNCT",
        "xpos": ",",
        "head": 5,
        "deprel": "punct",
        "misc": "start_char=15|end_char=16"
      },
      "be": {
        "id": "5",
        "text": "is",
        "lemma": "be",
        "upos": "VERB",
        "xpos": "VBZ",
        "feats": "Mood=Ind|Number=Sing|Person=3|Tense=Pres|VerbForm=Fin",
        "head": 0,
        "deprel": "root",
        "misc": "start_char=17|end_char=19"
      },
      "there": {
        "id": "6",
        "text": "there",
        "lemma": "there",
        "upos": "PRON",
        "xpos": "EX",
        "head": 5,
        "deprel": "expl",
        "misc": "start_char=20|end_char=25"
      },
      "anything": {
        "id": "7",
        "text": "anything",
        "lemma": "anything",
        "upos": "PRON",
        "xpos": "NN",
        "feats": "Number=Sing",
        "head": 5,
        "deprel": "nsubj",
        "misc": "start_char=26|end_char=34"
      },
      "else": {
        "id": "8",
        "text": "else",
        "lemma": "else",
        "upos": "ADJ",
        "xpos": "JJ",
        "feats": "Degree=Pos",
        "head": 7,
        "deprel": "amod",
        "misc": "start_char=35|end_char=39"
      },
      "I": {
        "id": "9",
        "text": "I",
        "lemma": "I",
        "upos": "PRON",
        "xpos": "PRP",
        "feats": "Case=Nom|Number=Sing|Person=1|PronType=Prs",
        "head": 11,
        "deprel": "nsubj",
        "misc": "start_char=40|end_char=41"
      },
      "can": {
        "id": "10",
        "text": "can",
        "lemma": "can",
        "upos": "AUX",
        "xpos": "MD",
        "feats": "VerbForm=Fin",
        "head": 11,
        "deprel": "aux",
        "misc": "start_char=42|end_char=45"
      },
      "help": {
        "id": "11",
        "text": "help",
        "lemma": "help",
        "upos": "VERB",
        "xpos": "VB",
        "feats": "VerbForm=Inf",
        "head": 7,
        "deprel": "acl:relcl",
        "misc": "start_char=46|end_char=50"
      },
      "you": {
        "id": "12",
        "text": "you",
        "lemma": "you",
        "upos": "PRON",
        "xpos": "PRP",
        "feats": "Case=Acc|Person=2|PronType=Prs",
        "head": 11,
        "deprel": "obj",
        "misc": "start_char=51|end_char=54"
      },
      "with": {
        "id": "13",
        "text": "with",
        "lemma": "with",
        "upos": "ADP",
        "xpos": "IN",
        "head": 11,
        "deprel": "obl",
        "misc": "start_char=55|end_char=59"
      },
      "?": {
        "id": "14",
        "text": "?",
        "lemma": "?",
        "upos": "PUNCT",
        "xpos": ".",
        "head": 5,
        "deprel": "punct",
        "misc": "start_char=59|end_char=60"
      }
    },
    "intent": "yes_no_question",
    "semantic_slot": "others",
    "topics": [
      "meantime",
      "anything",
      "I",
      "help"
    ]
  },
  {
    "turn": 24,
    "agent": "1",
    "text": "\"No That was it , Thank you so much for the good service\"",
    "tokens": {
      "no": {
        "id": "1",
        "text": "No",
        "lemma": "no",
        "upos": "INTJ",
        "xpos": "UH",
        "head": 0,
        "deprel": "root",
        "misc": "start_char=0|end_char=2"
      },
      "that": {
        "id": "1",
        "text": "That",
        "lemma": "that",
        "upos": "PRON",
        "xpos": "DT",
        "feats": "Number=Sing|PronType=Dem",
        "head": 3,
        "deprel": "nsubj",
        "misc": "start_char=3|end_char=7"
      },
      "be": {
        "id": "2",
        "text": "was",
        "lemma": "be",
        "upos": "AUX",
        "xpos": "VBD",
        "feats": "Mood=Ind|Number=Sing|Person=3|Tense=Past|VerbForm=Fin",
        "head": 3,
        "deprel": "cop",
        "misc": "start_char=8|end_char=11"
      },
      "it": {
        "id": "3",
        "text": "it",
        "lemma": "it",
        "upos": "PRON",
        "xpos": "PRP",
        "feats": "Case=Acc|Gender=Neut|Number=Sing|Person=3|PronType=Prs",
        "head": 0,
        "deprel": "root",
        "misc": "start_char=12|end_char=14"
      },
      ",": {
        "id": "4",
        "text": ",",
        "lemma": ",",
        "upos": "PUNCT",
        "xpos": ",",
        "head": 5,
        "deprel": "punct",
        "misc": "start_char=15|end_char=16"
      },
      "thank": {
        "id": "5",
        "text": "Thank",
        "lemma": "thank",
        "upos": "VERB",
        "xpos": "VBP",
        "feats": "Mood=Ind|Tense=Pres|VerbForm=Fin",
        "head": 3,
        "deprel": "parataxis",
        "misc": "start_char=17|end_char=22"
      },
      "you": {
        "id": "6",
        "text": "you",
        "lemma": "you",
        "upos": "PRON",
        "xpos": "PRP",
        "feats": "Case=Acc|Person=2|PronType=Prs",
        "head": 5,
        "deprel": "obj",
        "misc": "start_char=23|end_char=26"
      },
      "so": {
        "id": "7",
        "text": "so",
        "lemma": "so",
        "upos": "ADV",
        "xpos": "RB",
        "head": 8,
        "deprel": "advmod",
        "misc": "start_char=27|end_char=29"
      },
      "much": {
        "id": "8",
        "text": "much",
        "lemma": "much",
        "upos": "ADV",
        "xpos": "RB",
        "head": 5,
        "deprel": "advmod",
        "misc": "start_char=30|end_char=34"
      },
      "for": {
        "id": "9",
        "text": "for",
        "lemma": "for",
        "upos": "ADP",
        "xpos": "IN",
        "head": 12,
        "deprel": "case",
        "misc": "start_char=35|end_char=38"
      },
      "the": {
        "id": "10",
        "text": "the",
        "lemma": "the",
        "upos": "DET",
        "xpos": "DT",
        "feats": "Definite=Def|PronType=Art",
        "head": 12,
        "deprel": "det",
        "misc": "start_char=39|end_char=42"
      },
      "good": {
        "id": "11",
        "text": "good",
        "lemma": "good",
        "upos": "ADJ",
        "xpos": "JJ",
        "feats": "Degree=Pos",
        "head": 12,
        "deprel": "amod",
        "misc": "start_char=43|end_char=47"
      },
      "service": {
        "id": "12",
        "text": "service",
        "lemma": "service",
        "upos": "NOUN",
        "xpos": "NN",
        "feats": "Number=Sing",
        "head": 5,
        "deprel": "obl",
        "misc": "start_char=48|end_char=55"
      }
    },
    "intent": "negative_answer",
    "semantic_slot": "others",
    "topics": [
      "thank",
      "service"
    ]
  },
  {
    "turn": 25,
    "agent": "0",
    "text": "You're welcome.",
    "tokens": {
      "you": {
        "id": "1",
        "text": "You",
        "lemma": "you",
        "upos": "PRON",
        "xpos": "PRP",
        "feats": "Case=Nom|Person=2|PronType=Prs",
        "head": 3,
        "deprel": "nsubj",
        "misc": "start_char=0|end_char=3"
      },
      "be": {
        "id": "2",
        "text": "'re",
        "lemma": "be",
        "upos": "AUX",
        "xpos": "VBP",
        "feats": "Mood=Ind|Tense=Pres|VerbForm=Fin",
        "head": 3,
        "deprel": "cop",
        "misc": "start_char=3|end_char=6"
      },
      "welcome": {
        "id": "3",
        "text": "welcome",
        "lemma": "welcome",
        "upos": "ADJ",
        "xpos": "JJ",
        "feats": "Degree=Pos",
        "head": 0,
        "deprel": "root",
        "misc": "start_char=7|end_char=14"
      },
      ".": {
        "id": "4",
        "text": ".",
        "lemma": ".",
        "upos": "PUNCT",
        "xpos": ".",
        "head": 3,
        "deprel": "punct",
        "misc": "start_char=14|end_char=15"
      }
    },
    "intent": "response_to_thanking",
    "semantic_slot": "others",
    "topics": [
      "you",
      "be"
    ]
  },
  {
    "turn": 26,
    "agent": "0",
    "text": "Would you like to participate in a survey?",
    "tokens": {
      "would": {
        "id": "1",
        "text": "Would",
        "lemma": "would",
        "upos": "AUX",
        "xpos": "MD",
        "feats": "VerbForm=Fin",
        "head": 3,
        "deprel": "aux",
        "misc": "start_char=0|end_char=5"
      },
      "you": {
        "id": "2",
        "text": "you",
        "lemma": "you",
        "upos": "PRON",
        "xpos": "PRP",
        "feats": "Case=Nom|Person=2|PronType=Prs",
        "head": 3,
        "deprel": "nsubj",
        "misc": "start_char=6|end_char=9"
      },
      "like": {
        "id": "3",
        "text": "like",
        "lemma": "like",
        "upos": "VERB",
        "xpos": "VB",
        "feats": "VerbForm=Inf",
        "head": 0,
        "deprel": "root",
        "misc": "start_char=10|end_char=14"
      },
      "to": {
        "id": "4",
        "text": "to",
        "lemma": "to",
        "upos": "PART",
        "xpos": "TO",
        "head": 5,
        "deprel": "mark",
        "misc": "start_char=15|end_char=17"
      },
      "participate": {
        "id": "5",
        "text": "participate",
        "lemma": "participate",
        "upos": "VERB",
        "xpos": "VB",
        "feats": "VerbForm=Inf",
        "head": 3,
        "deprel": "xcomp",
        "misc": "start_char=18|end_char=29"
      },
      "in": {
        "id": "6",
        "text": "in",
        "lemma": "in",
        "upos": "ADP",
        "xpos": "IN",
        "head": 8,
        "deprel": "case",
        "misc": "start_char=30|end_char=32"
      },
      "a": {
        "id": "7",
        "text": "a",
        "lemma": "a",
        "upos": "DET",
        "xpos": "DT",
        "feats": "Definite=Ind|PronType=Art",
        "head": 8,
        "deprel": "det",
        "misc": "start_char=33|end_char=34"
      },
      "survey": {
        "id": "8",
        "text": "survey",
        "lemma": "survey",
        "upos": "NOUN",
        "xpos": "NN",
        "feats": "Number=Sing",
        "head": 5,
        "deprel": "obl",
        "misc": "start_char=35|end_char=41"
      },
      "?": {
        "id": "9",
        "text": "?",
        "lemma": "?",
        "upos": "PUNCT",
        "xpos": ".",
        "head": 3,
        "deprel": "punct",
        "misc": "start_char=41|end_char=42"
      }
    },
    "intent": "yes_no_question",
    "semantic_slot": "others",
    "topics": [
      "like",
      "participate",
      "survey"
    ]
  },
  {
    "turn": 27,
    "agent": "1",
    "text": "Sure will",
    "tokens": {
      "sure": {
        "id": "1",
        "text": "Sure",
        "lemma": "sure",
        "upos": "INTJ",
        "xpos": "UH",
        "head": 0,
        "deprel": "root",
        "misc": "start_char=0|end_char=4"
      },
      "will": {
        "id": "2",
        "text": "will",
        "lemma": "will",
        "upos": "AUX",
        "xpos": "MD",
        "feats": "VerbForm=Fin",
        "head": 1,
        "deprel": "aux",
        "misc": "start_char=5|end_char=9"
      }
    },
    "intent": "positive_answer",
    "semantic_slot": "others",
    "topics": []
  },
  {
    "turn": 28,
    "agent": "0",
    "text": "\"Thank you, the survey link will be sent to your email.\"",
    "tokens": {
      "thank": {
        "id": "1",
        "text": "Thank",
        "lemma": "thank",
        "upos": "VERB",
        "xpos": "VBP",
        "feats": "Mood=Ind|Tense=Pres|VerbForm=Fin",
        "head": 0,
        "deprel": "root",
        "misc": "start_char=0|end_char=5"
      },
      "you": {
        "id": "11",
        "text": "your",
        "lemma": "you",
        "upos": "PRON",
        "xpos": "PRP$",
        "feats": "Person=2|Poss=Yes|PronType=Prs",
        "head": 12,
        "deprel": "nmod:poss",
        "misc": "start_char=43|end_char=47"
      },
      ",": {
        "id": "3",
        "text": ",",
        "lemma": ",",
        "upos": "PUNCT",
        "xpos": ",",
        "head": 1,
        "deprel": "punct",
        "misc": "start_char=9|end_char=10"
      },
      "the": {
        "id": "4",
        "text": "the",
        "lemma": "the",
        "upos": "DET",
        "xpos": "DT",
        "feats": "Definite=Def|PronType=Art",
        "head": 6,
        "deprel": "det",
        "misc": "start_char=11|end_char=14"
      },
      "survey": {
        "id": "5",
        "text": "survey",
        "lemma": "survey",
        "upos": "NOUN",
        "xpos": "NN",
        "feats": "Number=Sing",
        "head": 6,
        "deprel": "compound",
        "misc": "start_char=15|end_char=21"
      },
      "link": {
        "id": "6",
        "text": "link",
        "lemma": "link",
        "upos": "NOUN",
        "xpos": "NN",
        "feats": "Number=Sing",
        "head": 9,
        "deprel": "nsubj:pass",
        "misc": "start_char=22|end_char=26"
      },
      "will": {
        "id": "7",
        "text": "will",
        "lemma": "will",
        "upos": "AUX",
        "xpos": "MD",
        "feats": "VerbForm=Fin",
        "head": 9,
        "deprel": "aux",
        "misc": "start_char=27|end_char=31"
      },
      "be": {
        "id": "8",
        "text": "be",
        "lemma": "be",
        "upos": "AUX",
        "xpos": "VB",
        "feats": "VerbForm=Inf",
        "head": 9,
        "deprel": "aux:pass",
        "misc": "start_char=32|end_char=34"
      },
      "send": {
        "id": "9",
        "text": "sent",
        "lemma": "send",
        "upos": "VERB",
        "xpos": "VBN",
        "feats": "Tense=Past|VerbForm=Part|Voice=Pass",
        "head": 1,
        "deprel": "parataxis",
        "misc": "start_char=35|end_char=39"
      },
      "to": {
        "id": "10",
        "text": "to",
        "lemma": "to",
        "upos": "ADP",
        "xpos": "IN",
        "head": 12,
        "deprel": "case",
        "misc": "start_char=40|end_char=42"
      },
      "email": {
        "id": "12",
        "text": "email",
        "lemma": "email",
        "upos": "NOUN",
        "xpos": "NN",
        "feats": "Number=Sing",
        "head": 9,
        "deprel": "obl",
        "misc": "start_char=48|end_char=53"
      },
      ".": {
        "id": "13",
        "text": ".",
        "lemma": ".",
        "upos": "PUNCT",
        "xpos": ".",
        "head": 1,
        "deprel": "punct",
        "misc": "start_char=53|end_char=54"
      }
    },
    "intent": "thanking",
    "semantic_slot": "others",
    "topics": [
      "thank",
      "survey",
      "link",
      "send",
      "email"
    ]
  },
  {
    "turn": 29,
    "agent": "0",
    "text": "Have a great day!",
    "tokens": {
      "have": {
        "id": "1",
        "text": "Have",
        "lemma": "have",
        "upos": "VERB",
        "xpos": "VB",
        "feats": "Mood=Imp|VerbForm=Fin",
        "head": 0,
        "deprel": "root",
        "misc": "start_char=0|end_char=4"
      },
      "a": {
        "id": "2",
        "text": "a",
        "lemma": "a",
        "upos": "DET",
        "xpos": "DT",
        "feats": "Definite=Ind|PronType=Art",
        "head": 4,
        "deprel": "det",
        "misc": "start_char=5|end_char=6"
      },
      "great": {
        "id": "3",
        "text": "great",
        "lemma": "great",
        "upos": "ADJ",
        "xpos": "JJ",
        "feats": "Degree=Pos",
        "head": 4,
        "deprel": "amod",
        "misc": "start_char=7|end_char=12"
      },
      "day": {
        "id": "4",
        "text": "day",
        "lemma": "day",
        "upos": "NOUN",
        "xpos": "NN",
        "feats": "Number=Sing",
        "head": 1,
        "deprel": "obj",
        "misc": "start_char=13|end_char=16"
      },
      "!": {
        "id": "5",
        "text": "!",
        "lemma": "!",
        "upos": "PUNCT",
        "xpos": ".",
        "head": 1,
        "deprel": "punct",
        "misc": "start_char=16|end_char=17"
      }
    },
    "intent": "closing",
    "semantic_slot": "others",
    "topics": [
      "have",
      "day"
    ]
  },
  {
    "turn": 30,
    "agent": "1",
    "text": "Thank you and you have a great day !",
    "tokens": {
      "thank": {
        "id": "1",
        "text": "Thank",
        "lemma": "thank",
        "upos": "VERB",
        "xpos": "VBP",
        "feats": "Mood=Ind|Tense=Pres|VerbForm=Fin",
        "head": 0,
        "deprel": "root",
        "misc": "start_char=0|end_char=5"
      },
      "you": {
        "id": "4",
        "text": "you",
        "lemma": "you",
        "upos": "PRON",
        "xpos": "PRP",
        "feats": "Case=Nom|Person=2|PronType=Prs",
        "head": 5,
        "deprel": "nsubj",
        "misc": "start_char=14|end_char=17"
      },
      "and": {
        "id": "3",
        "text": "and",
        "lemma": "and",
        "upos": "CCONJ",
        "xpos": "CC",
        "head": 5,
        "deprel": "cc",
        "misc": "start_char=10|end_char=13"
      },
      "have": {
        "id": "5",
        "text": "have",
        "lemma": "have",
        "upos": "VERB",
        "xpos": "VBP",
        "feats": "Mood=Ind|Tense=Pres|VerbForm=Fin",
        "head": 1,
        "deprel": "conj",
        "misc": "start_char=18|end_char=22"
      },
      "a": {
        "id": "6",
        "text": "a",
        "lemma": "a",
        "upos": "DET",
        "xpos": "DT",
        "feats": "Definite=Ind|PronType=Art",
        "head": 8,
        "deprel": "det",
        "misc": "start_char=23|end_char=24"
      },
      "great": {
        "id": "7",
        "text": "great",
        "lemma": "great",
        "upos": "ADJ",
        "xpos": "JJ",
        "feats": "Degree=Pos",
        "head": 8,
        "deprel": "amod",
        "misc": "start_char=25|end_char=30"
      },
      "day": {
        "id": "8",
        "text": "day",
        "lemma": "day",
        "upos": "NOUN",
        "xpos": "NN",
        "feats": "Number=Sing",
        "head": 5,
        "deprel": "obj",
        "misc": "start_char=31|end_char=34"
      },
      "!": {
        "id": "9",
        "text": "!",
        "lemma": "!",
        "upos": "PUNCT",
        "xpos": ".",
        "head": 1,
        "deprel": "punct",
        "misc": "start_char=35|end_char=36"
      }
    },
    "intent": "thanking",
    "semantic_slot": "others",
    "topics": [
      "thank",
      "day"
    ]
  }
]